odoo/addons/crm_salesperson_planner/README.rst
odoo/addons/crm_salesperson_planner/__init__.py
odoo/addons/crm_salesperson_planner/__manifest__.py
odoo/addons/crm_salesperson_planner/data/crm_salesperson_planner_sequence.xml
odoo/addons/crm_salesperson_planner/data/ir_cron_data.xml
odoo/addons/crm_salesperson_planner/i18n/crm_salesperson_planner.pot
odoo/addons/crm_salesperson_planner/i18n/es.po
odoo/addons/crm_salesperson_planner/i18n/it.po
odoo/addons/crm_salesperson_planner/models/__init__.py
odoo/addons/crm_salesperson_planner/models/calendar_event.py
odoo/addons/crm_salesperson_planner/models/crm_lead.py
odoo/addons/crm_salesperson_planner/models/crm_salesperson_planner_visit.py
odoo/addons/crm_salesperson_planner/models/crm_salesperson_planner_visit_close_reason.py
odoo/addons/crm_salesperson_planner/models/crm_salesperson_planner_visit_template.py
odoo/addons/crm_salesperson_planner/models/res_partner.py
odoo/addons/crm_salesperson_planner/readme/CONFIGURE.rst
odoo/addons/crm_salesperson_planner/readme/CONTRIBUTORS.rst
odoo/addons/crm_salesperson_planner/readme/DESCRIPTION.rst
odoo/addons/crm_salesperson_planner/readme/USAGE.rst
odoo/addons/crm_salesperson_planner/security/crm_salesperson_planner_security.xml
odoo/addons/crm_salesperson_planner/security/ir.model.access.csv
odoo/addons/crm_salesperson_planner/static/description/icon.png
odoo/addons/crm_salesperson_planner/static/description/index.html
odoo/addons/crm_salesperson_planner/tests/__init__.py
odoo/addons/crm_salesperson_planner/tests/test_crm_salesperson_planner_visit.py
odoo/addons/crm_salesperson_planner/tests/test_crm_salesperson_planner_visit_template.py
odoo/addons/crm_salesperson_planner/views/crm_lead.xml
odoo/addons/crm_salesperson_planner/views/crm_salesperson_planner_menu.xml
odoo/addons/crm_salesperson_planner/views/crm_salesperson_planner_visit_close_reason_views.xml
odoo/addons/crm_salesperson_planner/views/crm_salesperson_planner_visit_template_views.xml
odoo13_addon_crm_salesperson_planner-13.0.1.0.1.dev14.dist-info/METADATA
odoo13_addon_crm_salesperson_planner-13.0.1.0.1.dev14.dist-info/WHEEL
odoo13_addon_crm_salesperson_planner-13.0.1.0.1.dev14.dist-info/top_level.txt
odoo13_addon_crm_salesperson_planner-13.0.1.0.1.dev14.dist-info/RECORD
